mugem/__init__.py
mugem-3.0.dist-info/licenses/LICENSE
mugem-3.0.dist-info/METADATA
mugem-3.0.dist-info/WHEEL
mugem-3.0.dist-info/top_level.txt
mugem-3.0.dist-info/RECORD
