Metadata-Version: 2.4
Name: mugem
Version: 3.0
Summary: Multiplicative Generative Method (MGM)
Author: Rohit Kumar Behera
Author-email: rohitmbl24@gmail.com
Classifier: Programming Language :: Python :: 3
Classifier: Operating System :: OS Independent
Requires-Python: >=3.6
License-File: LICENSE
Dynamic: author
Dynamic: author-email
Dynamic: classifier
Dynamic: description
Dynamic: description-content-type
Dynamic: license-file
Dynamic: requires-python
Dynamic: summary
